{
"type": "FeatureCollection", 
"features": [
{"type": "Feature", "id": 0, "properties": {"index": "0","year": "1810","buyer": "Jean-Guillaume Moitte, French, 1746 - 1810 [sold, Moitte sale, Paris, France, June 7, 1810, lot 20.]","address": "Paris; France"}, "geometry": { "type": "Point","coordinates": [2.3522218999999995, 48.856614] } },
{"type": "Feature", "id": 1, "properties": {"index": "1","year": "1830","buyer": "M. Coutan [sold, Coutan sale, Paris, France, April 19, 1830, lot 182.]","address": "Paris; France"}, "geometry": { "type": "Point","coordinates": [2.3622218999999998, 48.868614] } },
{"type": "Feature", "id": 2, "properties": {"index": "4","year": "1854","buyer": "[J.?] Dumont [sold, Dumont sale, Paris, France, February 13, 1854, lot 118.]","address": "Paris; France"}, "geometry": { "type": "Point","coordinates": [2.3602218999999995, 48.846614] } },
{"type": "Feature", "id": 3, "properties": {"index": "5","year": "1861","buyer": "M. Flury-Herard [sold, Flury-Herard sale, Paris, France, May 13, 1861, lot 465.]","address": "Paris; France"}, "geometry": { "type": "Point","coordinates": [2.3382218999999997, 48.848614000000005] } },
{"type": "Feature", "id": 4, "properties": {"index": "7","year": "1870","buyer": "Thomas de Dreux [sold, Dreux sale, Paris, France, February 4, 1870, lot 28.]","address": "Paris; France"}, "geometry": { "type": "Point","coordinates": [2.3622218999999998, 48.858614] } },
{"type": "Feature", "id": 5, "properties": {"index": "8","year": "1983","buyer": "Private Collection [sold, Hôtel Druout, Paris, March 22, 1983, lot 2, to the J. Paul Getty Museum.]","address": "Paris; France"}, "geometry": { "type": "Point","coordinates": [2.3342218999999997, 48.866614] } },
{"type": "Feature", "id": 6, "properties": {"index": "10","year": "1983","buyer": "Getty Museum collections","address": "The Getty Museum; LA; US"}, "geometry": { "type": "Point","coordinates": [-118.473923738619, 34.0789066655244] } }
]}